Metadata-Version: 2.1
Name: pybraille
Version: 1.0.0
Summary: A library to convert text to 6-dot braille pattern(Grade 1)
Home-page: https://github.com/vineethsubbaraya/pybraille
Author: Vineeth Subbaraya
Author-email: vsubbaraya033@gmail.com
License: MIT
Keywords: python,braille,text to braille
Platform: UNKNOWN
Classifier: Development Status :: 5 - Production/Stable
Classifier: Intended Audience :: Education
Classifier: Operating System :: OS Independent
Classifier: License :: OSI Approved :: MIT License
Classifier: Programming Language :: Python :: 3
Classifier: Programming Language :: Python :: 3.5
Classifier: Programming Language :: Python :: 3.6
Classifier: Programming Language :: Python :: 3.7
Classifier: Programming Language :: Python :: 3.8
